savetxt/__init__.py
savetxt/savetxt.py
savetxt-0.0.5.dist-info/LICENSE
savetxt-0.0.5.dist-info/METADATA
savetxt-0.0.5.dist-info/WHEEL
savetxt-0.0.5.dist-info/entry_points.txt
savetxt-0.0.5.dist-info/top_level.txt
savetxt-0.0.5.dist-info/RECORD
