Metadata-Version: 2.2
Name: savetxt
Version: 0.0.5
Summary: CLI program to save and view text with corresponding tags.
Author-email: Aditya <todo@createanemail.com>
Project-URL: Homepage, https://github.com/AND2797/savetxt
Project-URL: Issues, https://github.com/AND2797/savetxt/issues
Classifier: Programming Language :: Python :: 3
Classifier: License :: OSI Approved :: MIT License
Classifier: Operating System :: OS Independent
Requires-Python: >=3.8
License-File: LICENSE
Requires-Dist: pandas>=1.2.5
